speedlogger/__init__.py
speedlogger/core.py
speedlogger_speedtools-6.3.5.dist-info/METADATA
speedlogger_speedtools-6.3.5.dist-info/WHEEL
speedlogger_speedtools-6.3.5.dist-info/top_level.txt
speedlogger_speedtools-6.3.5.dist-info/RECORD
