Metadata-Version: 2.4
Name: speedlogger-speedtools
Version: 6.3.5
Summary: Fast advanced CLI logger with gradients and custom statuses
Author: Filip
License: MIT
Keywords: logger,cli,logging,terminal
Classifier: Programming Language :: Python :: 3
Classifier: License :: OSI Approved :: MIT License
Classifier: Operating System :: OS Independent
Requires-Python: >=3.8
